terminado/__init__.py
terminado/management.py
terminado/uimod_embed.js
terminado/uimodule.py
terminado/websocket.py
terminado/_static/terminado.js
terminado/tests/__init__.py
terminado/tests/basic_test.py
terminado-0.13.3.dist-info/LICENSE
terminado-0.13.3.dist-info/METADATA
terminado-0.13.3.dist-info/WHEEL
terminado-0.13.3.dist-info/top_level.txt
terminado-0.13.3.dist-info/RECORD
